CHANGES.rst
CONTRIBUTORS.rst
README.rst
TODO.rst
goobook-3.5.4.data/data/share/man/man1/goobook.1
goobook-3.5.4.dist-info/METADATA
goobook-3.5.4.dist-info/WHEEL
goobook-3.5.4.dist-info/entry_points.txt
goobook-3.5.4.dist-info/licenses/LICENSE.txt
goobook/__init__.py
goobook/application.py
goobook/config.py
goobook/goobook.py
goobook/storage.py
goobook-3.5.4.dist-info/RECORD
