Metadata-Version: 2.4
Name: goobook
Version: 3.5.4
Summary: Search your google contacts from the command-line or mutt.
Keywords: abook,mutt,e-mail,gmail,google,address-book
Author-Email: =?utf-8?q?Christer_Sj=C3=B6holm?= <goobook2@gmail.com>
Maintainer-Email: Reuben Thomas <rrt@sc3d.org>
License-Expression: GPL-3.0-only
Classifier: Development Status :: 5 - Production/Stable
Classifier: Environment :: Console
Classifier: Operating System :: OS Independent
Classifier: Intended Audience :: End Users/Desktop
Classifier: Topic :: Communications :: Email :: Address Book
Requires-Python: <4.0,>=3.9
Requires-Dist: google-api-python-client~=2.0
Requires-Dist: simplejson~=3.16
Requires-Dist: setuptools>=62.6.0
Requires-Dist: pyxdg>=0.28
Requires-Dist: google-auth~=2.21
Requires-Dist: google-auth-oauthlib~=1.0
Requires-Dist: google-auth-httplib2~=0.1
